[
  {
    "coupon_name": "Flipkart Christmas Bonus Saver",
    "coupon_code": "FL123456",
    "target_vendor": "flipkart",
    "alternate_vendors": ["amazon", "meesho", "nykaa", "snapdeal"],
    "discount_rate": 20,
    "discount_amount": 0,
    "discount_limit": 5000,
    "description": ""
  },
  {
    "coupon_name": "Flipkart Saver Bonanza",
    "coupon_code": "FLAZ3456",
    "target_vendor": "flipkart",
    "alternate_vendors": ["amazon", "meesho", "nykaa", "snapdeal"],
    "discount_rate": 0,
    "discount_amount": 1000,
    "discount_limit": 1000,
    "description": ""
  },
  {
    "coupon_name": "Amazon Buy More Coupon",
    "coupon_code": "AMZ123456",
    "target_vendor": "amazon",
    "alternate_vendors": ["flipkart", "meesho", "nykaa", "snapdeal"],
    "discount_rate": 10,
    "discount_amount": 0,
    "discount_limit": 1000,
    "description": ""
  },
  {
    "coupon_name": "Amazon Grand Customer Coupon",
    "coupon_code": "AMAZING123",
    "target_vendor": "amazon",
    "alternate_vendors": ["flipkart", "meesho", "nykaa", "snapdeal"],
    "discount_rate": 0,
    "discount_amount": 5000,
    "discount_limit": 5000,
    "description": ""
  },
  {
    "coupon_name": "Meesho Customer Coupon",
    "coupon_code": "ME122001",
    "target_vendor": "meesho",
    "alternate_vendors": ["amazon", "flipkart", "nykaa", "snapdeal"],
    "discount_rate": 0,
    "discount_amount": 2000,
    "discount_limit": 2000,
    "description": ""
  },
  {
    "coupon_name": "Meesho Clearance Sale Coupon",
    "coupon_code": "MEESHO70DEL",
    "target_vendor": "meesho",
    "alternate_vendors": ["amazon", "flipkart", "nykaa", "snapdeal"],
    "discount_rate": 30,
    "discount_amount": 0,
    "discount_limit": 6000,
    "description": ""
  },
  {
    "coupon_name": "Zomato Food Delight Coupon",
    "coupon_code": "ZOMA129910",
    "target_vendor": "zomato",
    "alternate_vendors": ["swiggy", "dominos", "kfc"],
    "discount_rate": 20,
    "discount_amount": 0,
    "discount_limit": 500,
    "description": ""
  },
  {
    "coupon_name": "Zomato Foodie Vlogger Coupon",
    "coupon_code": "ZOM00123",
    "target_vendor": "zomato",
    "alternate_vendors": ["swiggy", "dominos", "kfc"],
    "discount_rate": 10,
    "discount_amount": 0,
    "discount_limit": 200,
    "description": ""
  },
  {
    "coupon_name": "Swiggy Foodie Bonanza Coupon",
    "coupon_code": "SWIGGY199910",
    "target_vendor": "swiggy",
    "alternate_vendors": ["zomato", "dominos", "kfc"],
    "discount_rate": 20,
    "discount_amount": 0,
    "discount_limit": 500,
    "description": ""
  },
  {
    "coupon_name": "Swiggy Tasters Paradise Coupon",
    "coupon_code": "SWI7777GY",
    "target_vendor": "swiggy",
    "alternate_vendors": ["zomato", "dominos", "kfc"],
    "discount_rate": 10,
    "discount_amount": 0,
    "discount_limit": 1000,
    "description": ""
  },
  {
    "coupon_name": "Practo Regular Customer Coupon",
    "coupon_code": "PRACTO2023",
    "target_vendor": "practo",
    "alternate_vendors": ["1mg", "medplus", "pharmeasy", "netmeds"],
    "discount_rate": 10,
    "discount_amount": 0,
    "discount_limit": 500,
    "description": ""
  },
  {
    "coupon_name": "1mg Medical Supplier Coupon",
    "coupon_code": "1MGDISCOUNT20",
    "target_vendor": "1mg",
    "alternate_vendors": ["practo", "medplus", "pharmeasy", "netmeds"],
    "discount_rate": 0,
    "discount_amount": 500,
    "discount_limit": 500,
    "description": ""
  },
  {
    "coupon_name": "Dream11 High Stakes Coupon",
    "coupon_code": "DREAM1120",
    "target_vendor": "dream11",
    "alternate_vendors": ["games2win", "99games", "mpl"],
    "discount_rate": 10,
    "discount_amount": 0,
    "discount_limit": 100,
    "description": ""
  },
  {
    "coupon_name": "Dream11 WC Fever Coupon",
    "coupon_code": "DREAM40YAY",
    "target_vendor": "dream11",
    "alternate_vendors": ["games2win", "99games", "mpl"],
    "discount_rate": 0,
    "discount_amount": 1000,
    "discount_limit": 1000,
    "description": ""
  },
  {
    "coupon_name": "99Games Gamble Coupon",
    "coupon_code": "99GAME20",
    "target_vendor": "99games",
    "alternate_vendors": ["games2win", "dream11", "mpl"],
    "discount_rate": 10,
    "discount_amount": 0,
    "discount_limit": 1000,
    "description": ""
  },
  {
    "coupon_name": "Rapido Daily Rider Coupon",
    "coupon_code": "RAPIDO2023DAILY",
    "target_vendor": "rapido",
    "alternate_vendors": ["uber", "ola"],
    "discount_rate": 10,
    "discount_amount": 0,
    "discount_limit": 50,
    "description": ""
  },
  {
    "coupon_name": "Rapido Privilege Coupon",
    "coupon_code": "RAPIDO0PRIVILEGE",
    "target_vendor": "rapido",
    "alternate_vendors": ["uber", "ola"],
    "discount_rate": 20,
    "discount_amount": 0,
    "discount_limit": 80,
    "description": ""
  },
  {
    "coupon_name": "Uber India Ride Coupon",
    "coupon_code": "UBER20BIKE",
    "target_vendor": "uber",
    "alternate_vendors": ["rapido", "ola"],
    "discount_rate": 10,
    "discount_amount": 0,
    "discount_limit": 50,
    "description": ""
  },
  {
    "coupon_name": "Netflix Christmas Super Sale",
    "coupon_code": "FLIXNCHILL40",
    "target_vendor": "netflix",
    "alternate_vendors": ["primevideo", "hotstar", "altbalaji"],
    "discount_rate": 40,
    "discount_amount": 0,
    "discount_limit": 400,
    "description": ""
  },
  {
    "coupon_name": "Amazon Prime Customers Delight Coupon",
    "coupon_code": "PRIMEVIDEO2023",
    "target_vendor": "primevideo",
    "alternate_vendors": ["netflix", "hotstar", "altbalaji"],
    "discount_rate": 10,
    "discount_amount": 0,
    "discount_limit": 200,
    "description": ""
  },
  {
    "coupon_name": "Amazon Prime Full Benefit Coupon",
    "coupon_code": "PRIME299",
    "target_vendor": "primevideo",
    "alternate_vendors": ["netflix", "hotstar", "altbalaji"],
    "discount_rate": 0,
    "discount_amount": 299,
    "discount_limit": 299,
    "description": ""
  }
]